urbanpy/__init__.py
urbanpy/accessibility/__init__.py
urbanpy/accessibility/accessibility.py
urbanpy/download/__init__.py
urbanpy/download/download.py
urbanpy/geom/__init__.py
urbanpy/geom/geom.py
urbanpy/plotting/__init__.py
urbanpy/plotting/plotting.py
urbanpy/routing/__init__.py
urbanpy/routing/routing.py
urbanpy/utils/__init__.py
urbanpy/utils/utils.py
urbanpy-0.2.1.dist-info/LICENSE.md
urbanpy-0.2.1.dist-info/METADATA
urbanpy-0.2.1.dist-info/WHEEL
urbanpy-0.2.1.dist-info/top_level.txt
urbanpy-0.2.1.dist-info/RECORD
