Metadata-Version: 2.1
Name: urbanpy
Version: 0.2.1
Summary: A library to download, process and visualize high resolution urban data.
Home-page: https://github.com/EL-BID/urbanpy
Author: Andres Regal, Claudio Ortega & Antonio Vasquez Brust
Author-email: a.regalludowieg@up.edu.pe
License: UNKNOWN
Platform: UNKNOWN
Classifier: Programming Language :: Python :: 3
Classifier: Operating System :: OS Independent
Requires-Python: >=3.6
Requires-Dist: geopandas
Requires-Dist: rtree
Requires-Dist: descartes
Requires-Dist: tqdm
Requires-Dist: h3
Requires-Dist: plotly
Requires-Dist: googlemaps
Requires-Dist: scikit-learn
Requires-Dist: osmnx
